{
    "draft": true,
    "title": "Ranger",
    "description": {
        "short": "With more bang per buck and power per pound, there are so many build options for the Ford Ranger midsize truck.",
        "long": "<p>With more bang per buck and power per pound, there are so many build options for the Ford Ranger midsize truck.</p><p>Whether you are simply looking to upgrade the appearance of your Ford Ranger or want to build a super capable off-road truck, THOR knows exactly how to execute the perfect build for you.</p>"
    },
    "make": "ford"
}
