{
    "slug": "f-250",
    "title": "F-250 Super Duty",
    "description": {
        "short": "Ford Super Duty trucks are some of the hardest working and best looking trucks on the road today.",
        "long": "<p>Ford Super Duty trucks are some of the hardest working and best looking trucks on the road today.</p><p>THOR outfits Super Duty trucks to do many different things with top line equipment like Carli Suspension, giving you comfort on the road and performance off road without sacrificing towing or cargo carrying capabilities.</p>"
    },
    "make": "ford",
    "images": {
        "featured": {
            "id": 427484,
            "image": 7
        }
    }
}
