{
	"date": "2022-10-28T00:00:00.000Z",
	"categories": [
		"suspension",
		"wheel-tire"
	],
	"related": [
		"662677-2022-ford-f-350",
		"782922-2022-ford-f-350",
		"588100-2022-ford-f-350"
	],
	"meta": {
		"year": 2021,
		"make": "ford",
		"model": "ford-f-350-super-duty",
		"trim": "Lariat",
		"color": "Grey",
		"drive": "4x4",
		"parts": [
			"Carli 3\" Backcountry Suspension Kit",
			"Carli Radius Arms",
			"Carli High Mount Steering Stabilizer",
			"Carli Low Mount Steering Stabilizer",
			"Carli Torsion Sway Bar",
			"Method MR305 18x9\" Wheels",
			"37x12.50R18 Nitto Ridge Grappler Tires"
		]
	},
	"images": {
		"total": 7,
		"snippet": 1,
		"highlight": [
			2,
			3
		]
	}
}